[
    {
        "date": "01/01",
        "href": "http://baike.baidu.com/view/3116.htm",
        "name": "元旦",
        "type": "中国传统节日"
    },
    {
        "date": "01/04",
        "href": "http://baike.baidu.com/view/63255.htm",
        "name": "黑人日",
        "type": "公众 / 国际节日"
    },
    {
        "date": "01/05",
        "href": "http://baike.baidu.com/subview/25902/5797898.htm",
        "name": "小寒",
        "type": "24节气"
    },
    {
        "date": "01/20",
        "href": "http://baike.baidu.com/view/25921.htm",
        "name": "大寒",
        "type": "24节气"
    },
    {
        "date": "01/25",
        "href": "http://baike.baidu.com/view/3108.htm",
        "name": "国际麻风节",
        "type": "公众 / 国际节日"
    },
    {
        "date": "腊月初八",
        "href": "http://baike.baidu.com/view/22439.htm",
        "name": "腊八节",
        "type": "中国传统节日"
    },
    {
        "date": "02/02",
        "href": "http://baike.baidu.com/view/22240.htm",
        "name": "世界湿地日",
        "type": "公众 / 国际节日"
    },
    {
        "date": "02/04",
        "href": "http://baike.baidu.com/view/25702.htm",
        "name": "立春",
        "type": "24节气"
    },
    {
        "date": "02/07",
        "href": "http://baike.baidu.com/view/59186.htm",
        "name": "国际声援南非日",
        "type": "公众 / 国际节日"
    },
    {
        "date": "02/10",
        "href": "http://baike.baidu.com/view/59198.htm",
        "name": "国际气象节",
        "type": "公众 / 国际节日"
    },
    {
        "date": "腊月廿三",
        "href": "http://baike.baidu.com/subview/15128/11122908.htm",
        "name": "小年",
        "type": "中国传统节日"
    },
    {
        "date": "02/14",
        "href": "http://baike.baidu.com/view/2533.htm",
        "name": "情人节",
        "type": "公众 / 国际节日"
    },
    {
        "date": "腊月三十",
        "href": "http://baike.baidu.com/view/2562.htm",
        "name": "除夕",
        "type": "中国传统节日"
    },
    {
        "date": "正月初一",
        "href": "http://baike.baidu.com/view/3108.htm",
        "name": "春节",
        "type": "中国传统节日"
    },
    {
        "date": "02/19",
        "href": "http://baike.baidu.com/view/10790.htm",
        "name": "雨水",
        "type": "24节气"
    },
    {
        "date": "02/24",
        "href": "http://baike.baidu.com/view/1273832.htm",
        "name": "第三世界青年日",
        "type": "公众 / 国际节日"
    },
    {
        "date": "02/28",
        "href": "http://baike.baidu.com/view/851778.htm",
        "name": "世界居住条件调查日",
        "type": "公众 / 国际节日"
    },
    {
        "date": "03/01",
        "href": "http://baike.baidu.com/view/182669.htm",
        "name": "国际海豹日",
        "type": "公众 / 国际节日"
    },
    {
        "date": "03/03",
        "href": "http://baike.baidu.com/view/63268.htm",
        "name": "全国爱耳日",
        "type": "公众 / 国际节日"
    },
    {
        "date": "正月十五",
        "href": "http://baike.baidu.com/view/1949.htm",
        "name": "元宵节",
        "type": "中国传统节日"
    },
    {
        "date": "03/05",
        "href": "http://baike.baidu.com/view/165596.htm",
        "name": "学雷锋日",
        "type": "公众 / 国际节日"
    },
    {
        "date": "03/06",
        "href": "http://baike.baidu.com/subview/21801/5837879.htm",
        "name": "惊蛰",
        "type": "24节气"
    },
    {
        "date": "03/08",
        "href": "http://baike.baidu.com/view/328605.htm",
        "name": "三八妇女节",
        "type": "公众 / 国际节日"
    },
    {
        "date": "03/12",
        "href": "http://baike.baidu.com/view/21813.htm",
        "name": "植树节",
        "type": "公众 / 国际节日"
    },
    {
        "date": "03/14",
        "href": "http://baike.baidu.com/view/9083.htm",
        "name": "白色情人节",
        "type": "公众 / 国际节日"
    },
    {
        "date": "03/15",
        "href": "http://baike.baidu.com/view/807967.htm",
        "name": "消费者权益日",
        "type": "公众 / 国际节日"
    },
    {
        "date": "03/17",
        "href": "http://baike.baidu.com/view/844278.htm",
        "name": "国际航海日",
        "type": "公众 / 国际节日"
    },
    {
        "date": "03/20",
        "href": "http://baike.baidu.com/view/3391343.htm",
        "name": "世界无肉日",
        "type": "公众 / 国际节日"
    },
    {
        "date": "03/21",
        "href": "http://baike.baidu.com/view/94034.htm",
        "name": "春分",
        "type": "24节气"
    },
    {
        "date": "03/21",
        "href": "http://baike.baidu.com/subview/26664/8839700.htm",
        "name": "龙抬头",
        "type": "24节气"
    },
    {
        "date": "03/21",
        "href": "http://baike.baidu.com/view/21357.htm",
        "name": "世界睡眠日",
        "type": "公众 / 国际节日"
    },
    {
        "date": "03/22",
        "href": "http://baike.baidu.com/view/21371.htm",
        "name": "世界水日",
        "type": "公众 / 国际节日"
    },
    {
        "date": "03/23",
        "href": "http://baike.baidu.com/view/25437.htm",
        "name": "世界气象日",
        "type": "公众 / 国际节日"
    },
    {
        "date": "04/01",
        "href": "http://baike.baidu.com/view/1710.htm",
        "name": "愚人节",
        "type": "公众 / 国际节日"
    },
    {
        "date": "04/02",
        "href": "http://baike.baidu.com/view/537990.htm",
        "name": "国际儿童图书日",
        "type": "公众 / 国际节日"
    },
    {
        "date": "四月初四",
        "href": "http://baike.baidu.com/view/318.htm",
        "name": "寒食节",
        "type": "中国传统节日"
    },
    {
        "date": "04/05",
        "href": "http://baike.baidu.com/view/3148.htm",
        "name": "清明节",
        "type": "中国传统节日"
    },
    {
        "date": "04/05",
        "href": "http://baike.baidu.com/view/1462.htm",
        "name": "复活节",
        "type": "公众 / 国际节日"
    },
    {
        "date": "04/07",
        "href": "http://baike.baidu.com/view/22478.htm",
        "name": "世界卫生日",
        "type": "公众 / 国际节日"
    },
    {
        "date": "04/11",
        "href": "http://baike.baidu.com/view/21386.htm",
        "name": "世界帕金森病日",
        "type": "公众 / 国际节日"
    },
    {
        "date": "04/20",
        "href": "http://baike.baidu.com/subview/11235/5615203.htm",
        "name": "谷雨",
        "type": "24节气"
    },
    {
        "date": "04/22",
        "href": "http://baike.baidu.com/view/2183.htm",
        "name": "世界地球日",
        "type": "公众 / 国际节日"
    },
    {
        "date": "04/23",
        "href": "http://baike.baidu.com/view/23287.htm",
        "name": "世界读书日",
        "type": "公众 / 国际节日"
    },
    {
        "date": "04/26",
        "href": "http://baike.baidu.com/view/2186.htm",
        "name": "知识产权日",
        "type": "公众 / 国际节日"
    },
    {
        "date": "04/26",
        "href": "http://baike.baidu.com/view/36429.htm",
        "name": "全国交通安全反思日",
        "type": "公众 / 国际节日"
    },
    {
        "date": "04/26",
        "href": "http://baike.baidu.com/view/27462.htm",
        "name": "世界儿童日",
        "type": "公众 / 国际节日"
    },
    {
        "date": "05/01",
        "href": "http://baike.baidu.com/view/44253.htm",
        "name": "国际劳动节",
        "type": "公众 / 国际节日"
    },
    {
        "date": "05/04",
        "href": "http://baike.baidu.com/view/27635.htm",
        "name": "五四青年节",
        "type": "公众 / 国际节日"
    },
    {
        "date": "05/06",
        "href": "http://baike.baidu.com/subview/25743/5723127.htm",
        "name": "立夏",
        "type": "24节气"
    },
    {
        "date": "四月初八",
        "href": "http://baike.baidu.com/view/240801.htm",
        "name": "佛诞日",
        "type": "中国传统节日"
    },
    {
        "date": "05/08",
        "href": "http://baike.baidu.com/view/26823.htm",
        "name": "世界红十字日",
        "type": "公众 / 国际节日"
    },
    {
        "date": "05/08",
        "href": "http://baike.baidu.com/view/100604.htm",
        "name": "世界微笑日",
        "type": "公众 / 国际节日"
    },
    {
        "date": "05/10",
        "href": "http://baike.baidu.com/view/2516.htm",
        "name": "母亲节",
        "type": "公众 / 国际节日"
    },
    {
        "date": "05/12",
        "href": "http://baike.baidu.com/view/25735.htm",
        "name": "国际护士节",
        "type": "公众 / 国际节日"
    },
    {
        "date": "05/15",
        "href": "http://baike.baidu.com/view/62008.htm",
        "name": "国际家庭日",
        "type": "公众 / 国际节日"
    },
    {
        "date": "05/17",
        "href": "http://baike.baidu.com/view/23216.htm",
        "name": "世界电信日",
        "type": "公众 / 国际节日"
    },
    {
        "date": "05/17",
        "href": "http://baike.baidu.com/view/21415.htm",
        "name": "全国助残日",
        "type": "公众 / 国际节日"
    },
    {
        "date": "05/18",
        "href": "http://baike.baidu.com/view/37249.htm",
        "name": "国际博物馆日",
        "type": "公众 / 国际节日"
    },
    {
        "date": "05/21",
        "href": "http://baike.baidu.com/subview/25760/8379312.htm",
        "name": "小满",
        "type": "24节气"
    },
    {
        "date": "05/30",
        "href": "http://baike.baidu.com/view/2340194.htm",
        "name": "五卅运动纪念",
        "type": "公众 / 国际节日"
    },
    {
        "date": "05/31",
        "href": "http://baike.baidu.com/view/22249.htm",
        "name": "世界无烟日",
        "type": "公众 / 国际节日"
    },
    {
        "date": "06/01",
        "href": "http://baike.baidu.com/view/16194.htm",
        "name": "六一儿童节",
        "type": "公众 / 国际节日"
    },
    {
        "date": "06/05",
        "href": "http://baike.baidu.com/view/22254.htm",
        "name": "世界环境日",
        "type": "公众 / 国际节日"
    },
    {
        "date": "06/06",
        "href": "http://baike.baidu.com/view/25774.htm",
        "name": "芒种",
        "type": "24节气"
    },
    {
        "date": "06/06",
        "href": "http://baike.baidu.com/view/21347.htm",
        "name": "全国爱眼日",
        "type": "公众 / 国际节日"
    },
    {
        "date": "06/11",
        "href": "http://baike.baidu.com/view/58964.htm",
        "name": "中国人口日",
        "type": "公众 / 国际节日"
    },
    {
        "date": "06/20",
        "href": "http://baike.baidu.com/view/294658.htm",
        "name": "世界难民日",
        "type": "公众 / 国际节日"
    },
    {
        "date": "五月初五",
        "href": "http://baike.baidu.com/view/2567.htm",
        "name": "端午节",
        "type": "中国传统节日"
    },
    {
        "date": "06/21",
        "href": "http://baike.baidu.com/view/8463.htm",
        "name": "父亲节",
        "type": "公众 / 国际节日"
    },
    {
        "date": "06/22",
        "href": "http://baike.baidu.com/subview/25782/6029524.htm",
        "name": "夏至",
        "type": "24节气"
    },
    {
        "date": "06/22",
        "href": "http://baike.baidu.com/view/2340240.htm",
        "name": "中国儿童慈善活动日",
        "type": "公众 / 国际节日"
    },
    {
        "date": "06/23",
        "href": "http://baike.baidu.com/view/37371.htm",
        "name": "国际奥林匹克日",
        "type": "公众 / 国际节日"
    },
    {
        "date": "06/25",
        "href": "http://baike.baidu.com/view/37338.htm",
        "name": "全国土地日",
        "type": "公众 / 国际节日"
    },
    {
        "date": "06/26",
        "href": "http://baike.baidu.com/view/106800.htm",
        "name": "国际禁毒日",
        "type": "公众 / 国际节日"
    },
    {
        "date": "06/30",
        "href": "http://baike.baidu.com/view/890704.htm",
        "name": "世界青年联欢节",
        "type": "公众 / 国际节日"
    },
    {
        "date": "07/01",
        "href": "http://baike.baidu.com/view/160972.html",
        "name": "中国共产党诞生日",
        "type": "公众 / 国际节日"
    },
    {
        "date": "07/01",
        "href": "http://baike.baidu.com/view/58870.htm",
        "name": "香港回归日",
        "type": "公众 / 国际节日"
    },
    {
        "date": "07/02",
        "href": "http://baike.baidu.com/view/160976.htm",
        "name": "国际体育记者日",
        "type": "公众 / 国际节日"
    },
    {
        "date": "07/06",
        "href": "http://baike.baidu.com/view/3926171.htm",
        "name": "国际接吻日",
        "type": "公众 / 国际节日"
    },
    {
        "date": "07/07",
        "href": "http://baike.baidu.com/view/80378.htm",
        "name": "抗日战争胜利纪念日",
        "type": "公众 / 国际节日"
    },
    {
        "date": "07/07",
        "href": "http://baike.baidu.com/view/25793.htm",
        "name": "小暑",
        "type": "24节气"
    },
    {
        "date": "07/11",
        "href": "http://baike.baidu.com/view/23435.htm",
        "name": "世界人口日",
        "type": "公众 / 国际节日"
    },
    {
        "date": "07/23",
        "href": "http://baike.baidu.com/subview/28060/5870595.htm",
        "name": "大暑",
        "type": "24节气"
    },
    {
        "date": "07/30",
        "href": "http://baike.baidu.com/view/160993.htm",
        "name": "非洲妇女日",
        "type": "公众 / 国际节日"
    },
    {
        "date": "08/01",
        "href": "http://baike.baidu.com/view/27204.htm",
        "name": "八一建军节",
        "type": "公众 / 国际节日"
    },
    {
        "date": "08/06",
        "href": "http://baike.baidu.com/view/923018.htm",
        "name": "国际电影节",
        "type": "公众 / 国际节日"
    },
    {
        "date": "08/08",
        "href": "http://baike.baidu.com/subview/25806/5840588.htm",
        "name": "立秋",
        "type": "24节气"
    },
    {
        "date": "08/15",
        "href": "http://baike.baidu.com/view/1387589.htm",
        "name": "日本投降日",
        "type": "公众 / 国际节日"
    },
    {
        "date": "七月初七",
        "href": "http://baike.baidu.com/view/8489.htm",
        "name": "七夕节",
        "type": "中国传统节日"
    },
    {
        "date": "08/23",
        "href": "http://baike.baidu.com/view/25819.htm",
        "name": "处暑",
        "type": "24节气"
    },
    {
        "date": "七月十五",
        "href": "http://baike.baidu.com/view/57902.htm",
        "name": "中元节",
        "type": "中国传统节日"
    },
    {
        "date": "09/03",
        "href": "http://baike.baidu.com/view/165610.htm",
        "name": "抗日胜利纪念日",
        "type": "公众 / 国际节日"
    },
    {
        "date": "09/08",
        "href": "http://www.baike.com/wiki/%E7%99%BD%E9%9C%B2",
        "name": "白露",
        "type": "24节气"
    },
    {
        "date": "09/08",
        "href": "http://baike.baidu.com/view/62062.htm",
        "name": "国际扫盲日",
        "type": "公众 / 国际节日"
    },
    {
        "date": "09/10",
        "href": "http://baike.baidu.com/view/25833.htm",
        "name": "教师节",
        "type": "公众 / 国际节日"
    },
    {
        "date": "09/12",
        "href": "http://baike.baidu.com/view/62054.htm",
        "name": "世界清洁地球日",
        "type": "公众 / 国际节日"
    },
    {
        "date": "09/12",
        "href": "http://baike.baidu.com/view/22443.htm",
        "name": "国际臭氧层保护日",
        "type": "公众 / 国际节日"
    },
    {
        "date": "09/16",
        "href": "http://baike.baidu.com/view/27269.htm",
        "name": "国际和平日",
        "type": "公众 / 国际节日"
    },
    {
        "date": "09/18",
        "href": "http://baike.baidu.com/view/62054.htm",
        "name": "\"九一八\"事变纪念日",
        "type": "公众 / 国际节日"
    },
    {
        "date": "09/20",
        "href": "http://baike.baidu.com/view/147917.htm",
        "name": "国际爱牙日",
        "type": "公众 / 国际节日"
    },
    {
        "date": "09/22",
        "href": "http://baike.baidu.com/view/489563.htm",
        "name": "世界无车日",
        "type": "公众 / 国际节日"
    },
    {
        "date": "09/23",
        "href": "http://baike.baidu.com/subview/11114/5833491.htm?fr=aladdin",
        "name": "秋分",
        "type": "24节气"
    },
    {
        "date": "八月十五",
        "href": "http://baike.baidu.com/view/2568.htm",
        "name": "中秋节",
        "type": "中国传统节日"
    },
    {
        "date": "09/27",
        "href": "http://baike.baidu.com/view/59496.htm",
        "name": "世界旅游日",
        "type": "公众 / 国际节日"
    },
    {
        "date": "09/28",
        "href": "http://baike.baidu.com/view/62032.htm",
        "name": "国际聋人节",
        "type": "公众 / 国际节日"
    },
    {
        "date": "10/01",
        "href": "http://baike.baidu.com/view/14446.htm",
        "name": "国庆节",
        "type": "公众 / 国际节日"
    },
    {
        "date": "10/04",
        "href": "http://baike.baidu.com/view/59207.htm",
        "name": "世界动物日",
        "type": "公众 / 国际节日"
    },
    {
        "date": "10/08",
        "href": "http://baike.baidu.com/view/25838.htm",
        "name": "寒露",
        "type": "24节气"
    },
    {
        "date": "10/09",
        "href": "http://baike.baidu.com/view/26600.htm",
        "name": "世界邮政日",
        "type": "公众 / 国际节日"
    },
    {
        "date": "10/10",
        "href": "http://baike.baidu.com/view/59004.htm",
        "name": "辛亥革命纪念日",
        "type": "公众 / 国际节日"
    },
    {
        "date": "10/13",
        "href": "http://baike.baidu.com/view/1917206.htm",
        "name": "中国少年先锋队诞辰日",
        "type": "公众 / 国际节日"
    },
    {
        "date": "10/14",
        "href": "http://baike.baidu.com/view/158147.htm",
        "name": "世界标准日",
        "type": "公众 / 国际节日"
    },
    {
        "date": "10/15",
        "href": "http://baike.baidu.com/view/21456.htm",
        "name": "国际盲人节",
        "type": "公众 / 国际节日"
    },
    {
        "date": "10/16",
        "href": "http://baike.baidu.com/view/124252.htm",
        "name": "世界粮食日",
        "type": "公众 / 国际节日"
    },
    {
        "date": "10/17",
        "href": "http://baike.baidu.com/view/101733.htm?fromId=165572",
        "name": "国际消除贫困日",
        "type": "公众 / 国际节日"
    },
    {
        "date": "九月初九",
        "href": "http://baike.baidu.com/view/2572.htm",
        "name": "重阳节",
        "type": "中国传统节日"
    },
    {
        "date": "10/22",
        "href": "http://baike.baidu.com/view/124255.htm",
        "name": "世界传统医药日",
        "type": "公众 / 国际节日"
    },
    {
        "date": "10/24",
        "href": "http://baike.baidu.com/subview/25848/5833534.htm",
        "name": "霜降",
        "type": "24节气"
    },
    {
        "date": "10/22",
        "href": "http://baike.baidu.com/view/59045.htm",
        "name": "联合国日",
        "type": "公众 / 国际节日"
    },
    {
        "date": "10/31",
        "href": "http://baike.baidu.com/view/522014.htm",
        "name": "世界勤俭日",
        "type": "公众 / 国际节日"
    },
    {
        "date": "10/31",
        "href": "http://baike.baidu.com/view/2532.htm",
        "name": "万圣节",
        "type": "公众 / 国际节日"
    },
    {
        "date": "11/08",
        "href": "http://baike.baidu.com/view/25856.htm",
        "name": "立冬",
        "type": "24节气"
    },
    {
        "date": "11/08",
        "href": "http://baike.baidu.com/view/45983.htm",
        "name": "中国记者日",
        "type": "公众 / 国际节日"
    },
    {
        "date": "11/10",
        "href": "http://baike.baidu.com/view/165356.htm",
        "name": "世界青年节",
        "type": "公众 / 国际节日"
    },
    {
        "date": "11/11",
        "href": "http://baike.baidu.com/view/23105.htm",
        "name": "光棍节",
        "type": "公众 / 国际节日"
    },
    {
        "date": "11/14",
        "href": "http://baike.baidu.com/view/22284.htm",
        "name": "世界糖尿病日",
        "type": "公众 / 国际节日"
    },
    {
        "date": "11/17",
        "href": "http://baike.baidu.com/view/165576.htm",
        "name": "国际大学生节",
        "type": "公众 / 国际节日"
    },
    {
        "date": "11/21",
        "href": "http://baike.baidu.com/view/59256.htm",
        "name": "世界问候日",
        "type": "公众 / 国际节日"
    },
    {
        "date": "11/22",
        "href": "http://baike.baidu.com/subview/25867/7072847.htm",
        "name": "小雪",
        "type": "24节气"
    },
    {
        "date": "11/26",
        "href": "http://baike.baidu.com/view/2525.htm",
        "name": "感恩节",
        "type": "公众 / 国际节日"
    },
    {
        "date": "12/01",
        "href": "http://baike.baidu.com/view/28884.htm",
        "name": "世界艾滋病日",
        "type": "公众 / 国际节日"
    },
    {
        "date": "12/03",
        "href": "http://baike.baidu.com/view/155500.htm",
        "name": "国际残疾人日",
        "type": "公众 / 国际节日"
    },
    {
        "date": "12/07",
        "href": "http://baike.baidu.com/subview/25884/6061367.htm?fr=aladdin",
        "name": "大雪",
        "type": "24节气"
    },
    {
        "date": "12/09",
        "href": "http://baike.baidu.com/view/59061.htm",
        "name": "\"一二九\"运动纪念日",
        "type": "公众 / 国际节日"
    },
    {
        "date": "12/09",
        "href": "http://baike.baidu.com/view/31273.htm",
        "name": "世界足球日",
        "type": "公众 / 国际节日"
    },
    {
        "date": "12/10",
        "href": "http://baike.baidu.com/view/59173.htm",
        "name": "世界人权日",
        "type": "公众 / 国际节日"
    },
    {
        "date": "12/12",
        "href": "http://baike.baidu.com/view/961033.htm",
        "name": "西安事变纪念日",
        "type": "公众 / 国际节日"
    },
    {
        "date": "12/13",
        "href": "http://baike.baidu.com/view/22274.htm",
        "name": "南京大屠杀",
        "type": "公众 / 国际节日"
    },
    {
        "date": "12/20",
        "href": "http://baike.baidu.com/view/80418.htm",
        "name": "澳门回归日",
        "type": "公众 / 国际节日"
    },
    {
        "date": "12/21",
        "href": "http://baike.baidu.com/view/22264.htm",
        "name": "国际篮球日",
        "type": "公众 / 国际节日"
    },
    {
        "date": "12/22",
        "href": "http://baike.baidu.com/view/16674.htm",
        "name": "冬至",
        "type": "24节气"
    },
    {
        "date": "12/24",
        "href": "http://baike.baidu.com/view/28259.htm",
        "name": "平安夜",
        "type": "公众 / 国际节日"
    },
    {
        "date": "12/25",
        "href": "http://baike.baidu.com/view/2547.htm",
        "name": "圣诞节",
        "type": "公众 / 国际节日"
    }
]