{"title": "保安为涉黑案嫌犯传消息获刑：递张纸条获出价20万和一套房", "link": "", "desc": "\r\n　　递张条子，给20万加一套房，这是湖南长沙涉黑专案嫌犯万某被监视居住期间，给看护他的保安开出的条件。入职仅两个月的保安班长扶笃先铤而走险，伙同其堂兄扶独前多次为嫌犯及其家属传递消息，同时收受巨额贿赂。", "pub_date": "2019-10-23 16:19:19"}
{"title": "安徽警方两架包机跨境押回116名电信诈骗嫌疑人", "link": "", "desc": "", "pub_date": "2019-10-23 16:17:46"}
{"title": "点击乌镇 洞见未来——从第六届互联网大会看智能互联新趋势", "link": "", "desc": "\r\n　　新华社杭州10月22日电 题：点击乌镇 洞见未来——从第六届互联网大会看智能互联新趋势", "pub_date": "2019-10-23 16:17:02"}
{"title": "全球四大会计师事务所悉数落子河南郑州", "link": "", "desc": "\r\n　　中新社郑州10月23日电 (记者 李贵刚)历经一年多的筹备，德勤郑州分公司23日正式落户河南省会郑州。至此，全球四大会计师事务所全部落子郑州的格局形成。", "pub_date": "2019-10-23 16:15:13"}
{"title": "精彩速递 好看视频任你选", "link": "", "desc": "", "pub_date": "2019-10-23 16:14:51"}
{"title": "英研究称空气污染超标 致心脏病及中风等病例激增", "link": "", "desc": "\r\n　　中新网10月23日电 据英国广播公司(BBC)中文网报道，近年来，科学界对空气污染给人体健康带来的危害——导致早亡、甚至让人变笨等等，似乎已经找到足够的证据和理论。最近，英国研究人员发现，每年在空气污染指数较高的日子里，医院接收的突发心脏病、中风以及急性哮喘病人的数量也会上升，进一步证实了污染与疾病之间的确凿联系。", "pub_date": "2019-10-23 16:13:29"}
{"title": "北京望坛棚户区改造项目发现明清时期墓葬", "link": "", "desc": " ", "pub_date": "2019-10-23 16:12:45"}
{"title": "即日生效！办理国管公积金提取不再提交纸质申请书", "link": "", "desc": "\r\n　　中新网10月23日电 23日，中央国家机关住房资金管理中心官网发布《关于简化住房公积金提取业务申请材料的公告》称，即日起，职工办理住房公积金提取业务时，不再提交纸质提取申请书。", "pub_date": "2019-10-23 16:11:18"}
{"title": "香港《逃犯条例》修订草案正式撤回", "link": "", "desc": "\r\n　　香港立法会10月23日召开会议，保安局局长李家超宣布撤回《逃犯条例》修订草案，为这条草案正式画上句号。撤回程序于下午2:57开始，3:01分完成整个程序，耗时仅五分钟。(央视记者 王梦)", "pub_date": "2019-10-23 16:10:06"}
{"title": "再见，乌镇！你好，未来！——第六届世界互联网大会圆满落下帷幕", "link": "", "desc": "\r\n　　新华社杭州10月22日电 题：再见，乌镇！你好，未来！——第六届世界互联网大会圆满落下帷幕", "pub_date": "2019-10-23 16:09:10"}
{"title": "236份“90后”遗嘱：游戏账号写进遗嘱 财产继承人大多是父母", "link": "", "desc": "\r\n　　236份“90后”遗嘱说了什么", "pub_date": "2019-10-23 16:08:36"}
{"title": "注重开门抓教育", "link": "", "desc": "\r\n　　注重开门抓教育", "pub_date": "2019-10-23 16:07:52"}
{"title": "澳昆州监狱袭警事件增多 或与新狱警经验不足有关", "link": "", "desc": "\r\n　　中新网10月23日电 据澳洲新快网23日报道，澳大利亚昆士兰州的狱警警告称，昆士兰监狱新招募的管教人员多数经验不足，或许是导致监狱工作人员被袭事件迅速增加的原因之一。", "pub_date": "2019-10-23 16:05:36"}
{"title": "女子遇车祸身亡家属难寻 32万赔偿金谁来管？", "link": "", "desc": "\r\n　　车祸身亡家属难寻 32万赔偿金谁来管", "pub_date": "2019-10-23 16:04:50"}
{"title": "张译：让观众认可方能凸显演员的价值", "link": "", "desc": "\r\n　　张译：让观众认可方能凸显演员的价值", "pub_date": "2019-10-23 16:02:25"}
{"title": "一移民船与希腊海岸警卫队巡逻艇相撞 已致1死6伤", "link": "", "desc": "\r\n　　中新网10月23日电 据法新社报道，希腊官员称，当地时间23日，一艘移民船与一艘希腊海岸警卫队巡逻艇相撞，已导致1名移民遇难，6人受伤，另有2人下落不明。", "pub_date": "2019-10-23 16:00:45"}
{"title": "中国多地前三季度对东盟贸易总值大幅增长", "link": "", "desc": "\r\n　　中新社重庆10月23日电 (记者 韩璐)中国多地陆续公布2019年前三季度外贸进出口数据。记者23日梳理发现，前三季度中国多地特别是西部省市与东盟贸易总值超两位数增长。", "pub_date": "2019-10-23 16:00:00"}
{"title": "2019国际网联世界巡回赛青少年年终总决赛成都开拍", "link": "", "desc": "\r\n　　中新社成都10月23日电 (记者 贺劭清)2019国际网联世界巡回赛青少年年终总决赛23日在成都开拍。中国选手郑钦文6：2、6：4战胜日本选手川口夏実，获得开门红。", "pub_date": "2019-10-23 15:58:41"}
{"title": "套路贷、电信诈骗、疫苗犯罪，最高法将严惩这些犯罪", "link": "", "desc": "\r\n　　今天上午，十三届全国人大常委会第十四次会议审议了最高法关于加强刑事审判工作情况的报告。", "pub_date": "2019-10-23 15:58:19"}
{"title": "副教授抄副教授：潍坊学院副教授被撤销职称调离教师岗位", "link": "", "desc": "\r\n　　潍坊学院传媒学院副教授杨洁的一本专著，被发现抄袭了太原师范学院文学院副教授郝建杰的博士论文。", "pub_date": "2019-10-23 15:57:13"}
{"title": "国家邮政局：基本实现村村直通邮 带动贫困户增收2.3亿元", "link": "", "desc": "\r\n　　今天，国家邮政局召开第四季度例行新闻发布会，国家邮政局机关党委副书记张星朝表示，截至目前，55万多个建制村的村民足不出村就可以收到邮件包裹，全国基本实现“村村直通邮”，乡镇快递网点覆盖率达到95%。国家邮政局大力促进邮政、快递服务现代农业，惠及438个国家级贫困县7.1万户贫困人口，带动贫困户增收2.3亿元。", "pub_date": "2019-10-23 15:55:49"}
{"title": "防范纠正冤错案件 2014年以来8000余件刑事案件被再审改判", "link": "", "desc": "\r\n　　中新网客户端10月23日(冷昊阳) 23日，最高人民法院院长周强在第十三届全国人民代表大会常务委员会第十四次会议上报告人民法院加强刑事审判工作情况。在依法防范和纠正冤错案件方面，2014年以来，人民法院依法纠正呼格吉勒图案、聂树斌案、陈满案等重大冤错案件42件63人，并依法予以国家赔偿。各级法院按照审判监督程序再审改判刑事案件8051件。依法宣告3246名公诉案件被告人和1986名自诉案件被告人无罪。", "pub_date": "2019-10-23 15:54:57"}
{"title": "NBA常规赛首日：猛龙加时胜鹈鹕 湖人不敌快船", "link": "", "desc": "\r\n\n当地时间10月5日，勇士队在新主场旧金山大通中心迎来2019-20NBA赛季季前赛首个对手湖人队。最终，勇士队以101：123大比分落败，未能取得新主场的开门红。图为湖人队戴维斯(左)和詹姆斯(中)在比赛中。 中新社记者 刘关关 摄\r\n\n　　中新网10月23日电 北京时间23日，NBA迎来两场揭幕战。最终卫冕冠军猛龙加时130:122险胜鹈鹕；湖人客场102:112不敌快船。", "pub_date": "2019-10-23 15:54:47"}
{"title": "外逃职务犯罪嫌疑人王世家回国投案并积极退赃", "link": "", "desc": "\r\n　　中新网10月23日电 据中央纪委国家监委网站消息，日前，在中央反腐败协调小组国际追逃追赃工作办公室统筹协调下，经辽宁省、大连市两级纪委监委不懈努力，外逃职务犯罪嫌疑人王世家回国投案，并积极退赃。", "pub_date": "2019-10-23 15:54:26"}
{"title": "国家邮政局：全面推动实名收寄验视和过机安检", "link": "", "desc": "\r\n　　国家邮政局今天举行第四季度新闻发布会，国家邮政局新闻发言人冯力虎表示，国家邮政局将全面推动落实收寄验视、实名收寄和过机安检“三项制度”，着力强化危险违禁物品寄递安全管控。", "pub_date": "2019-10-23 15:54:12"}
{"title": "人民法院严惩针对妇女儿童的暴力、虐待、性侵害等犯罪", "link": "", "desc": "\r\n　　中新网客户端10月23日电(冷昊阳) 23日，最高人民法院院长周强在第十三届全国人民代表大会常务委员会第十四次会议上报告人民法院加强刑事审判工作情况。在严惩针对妇女儿童的暴力、虐待、性侵害等犯罪方面，2014年以来，人民法院审结相关案件14.6万件，出台审理拐卖妇女儿童犯罪案件司法解释。严惩抢夺方向盘、殴打驾驶员等妨害安全驾驶的违法犯罪行为，依法审理涉高空抛物坠物刑事案件，出台办理考试作弊案件司法解释，依法审结连恩青、王英生等暴力伤医案件。", "pub_date": "2019-10-23 15:51:54"}
{"title": "波士顿华埠社区召开会议 探讨华埠历史文化保护", "link": "", "desc": "\r\n　　中新网10月23日电 据美国《世界日报》报道，日前，美国波士顿部分华埠社区组织举办“华埠历史暨文化保护讨论会”，约70名社区人士参与讨论并发表意见，思考华埠文化的意义与内涵，不同单位也就移民历史足迹、华埠工人铜像、华埠历史遗产中心等保护计划作了报告。", "pub_date": "2019-10-23 15:50:42"}
{"title": "意大利移民：学生居留明显增多 中国学生占比大", "link": "", "desc": "\r\n　　中国侨网10月23日电  据意大利《新欧洲侨报》报道，意大利统计局ISTAT的最新数据显示，2018年意大利新发居留24.2万多张，2017年近26.3万张，一年内减少7.9%。调查强调：申请庇护居留的减少了41.9%，但工作居留增加了19.7%，家属居留也增加了8.2%；与此同时，学生居留明显增多且增幅较大(增加20%)，其中以中国留学生居多。", "pub_date": "2019-10-23 15:50:10"}
{"title": "乐天集团名誉会长辛格浩申请停止服刑 韩检方接受", "link": "", "desc": "\r\n　　中新网10月23日电 据韩国国际广播电台(KBS)报道，韩国首尔地方中央检察厅23日表示，接受乐天集团名誉会长辛格浩提交的停止执行刑罚申请。此前，韩国大法院以涉嫌贪污渎职为由，判处辛格浩3年有期徒刑。", "pub_date": "2019-10-23 15:47:35"}
{"title": "小情侣闹分手互盗存款 两人最终均被刑事拘留", "link": "", "desc": "\r\n　　小情侣闹分手互盗存款被刑拘", "pub_date": "2019-10-23 15:46:53"}
